omserv/.omlish-manifests.json
omserv/README.md
omserv/__about__.py
omserv/__init__.py
omserv/apps/__init__.py
omserv/apps/base.py
omserv/apps/inject.py
omserv/apps/markers.py
omserv/apps/routes.py
omserv/apps/sessions.py
omserv/apps/templates.py
omserv/nginx/__init__.py
omserv/nginx/build.py
omserv/nginx/logs.py
omserv/nginx/stubstatus.py
omserv/nginx/patches/__init__.py
omserv/nginx/patches/nginx-1.28.0_http_status.patch
omserv/nodes/__init__.py
omserv/nodes/db.py
omserv/nodes/models.py
omserv/nodes/registry.py
omserv/nodes/sql.py
omserv/server/LICENSE
omserv/server/__init__.py
omserv/server/config.py
omserv/server/debug.py
omserv/server/default.py
omserv/server/events.py
omserv/server/headers.py
omserv/server/inject.py
omserv/server/lifespans.py
omserv/server/listener.py
omserv/server/multiprocess.py
omserv/server/server.py
omserv/server/sockets.py
omserv/server/ssl.py
omserv/server/taskspawner.py
omserv/server/types.py
omserv/server/workercontext.py
omserv/server/protocols/__init__.py
omserv/server/protocols/h11.py
omserv/server/protocols/h2.py
omserv/server/protocols/protocols.py
omserv/server/protocols/types.py
omserv/server/resources/__init__.py
omserv/server/resources/favicon.ico
omserv/server/streams/__init__.py
omserv/server/streams/httpstream.py
omserv/server/streams/utils.py
omserv/server/streams/wsstream.py
omserv-0.0.0.dev516.dist-info/licenses/LICENSE
omserv-0.0.0.dev516.dist-info/METADATA
omserv-0.0.0.dev516.dist-info/WHEEL
omserv-0.0.0.dev516.dist-info/entry_points.txt
omserv-0.0.0.dev516.dist-info/top_level.txt
omserv-0.0.0.dev516.dist-info/RECORD
