Metadata-Version: 2.4
Name: omserv
Version: 0.0.0.dev516
Summary: omserv
Author: wrmsr
License-Expression: BSD-3-Clause
Project-URL: source, https://github.com/wrmsr/omlish
Classifier: Development Status :: 2 - Pre-Alpha
Classifier: Intended Audience :: Developers
Classifier: Operating System :: OS Independent
Classifier: Operating System :: POSIX
Classifier: Programming Language :: Python :: 3
Classifier: Programming Language :: Python :: 3.13
Requires-Python: >=3.13
License-File: LICENSE
Requires-Dist: omlish==0.0.0.dev516
Provides-Extra: all
Requires-Dist: h11~=0.16; extra == "all"
Requires-Dist: h2~=4.3; extra == "all"
Requires-Dist: priority~=2.0; extra == "all"
Requires-Dist: wsproto~=1.3; extra == "all"
Requires-Dist: jinja2~=3.1; extra == "all"
Provides-Extra: server
Requires-Dist: h11~=0.16; extra == "server"
Requires-Dist: h2~=4.3; extra == "server"
Requires-Dist: priority~=2.0; extra == "server"
Requires-Dist: wsproto~=1.3; extra == "server"
Provides-Extra: templates
Requires-Dist: jinja2~=3.1; extra == "templates"
Dynamic: license-file
